[
    {
        "key": "dbln",
        "value": "%7B%2261552023033721%22%3A%22KBJsMxiL%22%7D",
        "domain": "facebook.com",
        "path": "/login/device-based/",
        "hostOnly": false,
        "creation": "2025-04-17T15:31:45.657Z",
        "lastAccessed": "2025-04-17T15:31:45.668Z"
    },
    {
        "key": "sb",
        "value": "kHXfZ82-9yVMLpOSzRi4QCFZ",
        "domain": "facebook.com",
        "path": "/",
        "hostOnly": false,
        "creation": "2025-04-17T15:31:45.668Z",
        "lastAccessed": "2025-04-17T15:31:45.668Z"
    },
    {
        "key": "datr",
        "value": "7RsBaMMf1yl8qWjbppMF99pl",
        "domain": "facebook.com",
        "path": "/",
        "hostOnly": false,
        "creation": "2025-04-17T15:31:45.668Z",
        "lastAccessed": "2025-04-17T15:31:45.668Z"
    },
    {
        "key": "m_pixel_ratio",
        "value": "3",
        "domain": "facebook.com",
        "path": "/",
        "hostOnly": false,
        "creation": "2025-04-17T15:31:45.668Z",
        "lastAccessed": "2025-04-17T15:31:45.669Z"
    },
    {
        "key": "ps_l",
        "value": "1",
        "domain": "facebook.com",
        "path": "/",
        "hostOnly": false,
        "creation": "2025-04-17T15:31:45.669Z",
        "lastAccessed": "2025-04-17T15:31:45.669Z"
    },
    {
        "key": "ps_n",
        "value": "1",
        "domain": "facebook.com",
        "path": "/",
        "hostOnly": false,
        "creation": "2025-04-17T15:31:45.669Z",
        "lastAccessed": "2025-04-17T15:31:45.669Z"
    },
    {
        "key": "c_user",
        "value": "61560265677014",
        "domain": "facebook.com",
        "path": "/",
        "hostOnly": false,
        "creation": "2025-04-17T15:31:45.669Z",
        "lastAccessed": "2025-04-17T15:31:45.669Z"
    },
    {
        "key": "fr",
        "value": "0BsgisV4i0CY0nWtl.AWd7ZxO72Ooo5EyQXRD0j8fPry6yrZ7Q0Cwd1FgyN_FdXpLR0WI.BoARvt..AAA.0.0.BoAR6T.AWftFZE3nb_aRaCrlBy4eU1pgNs",
        "domain": "facebook.com",
        "path": "/",
        "hostOnly": false,
        "creation": "2025-04-17T15:31:45.669Z",
        "lastAccessed": "2025-04-17T15:31:45.669Z"
    },
    {
        "key": "xs",
        "value": "11%3A5w7aLcN8c75jzg%3A2%3A1744903828%3A-1%3A7315",
        "domain": "facebook.com",
        "path": "/",
        "hostOnly": false,
        "creation": "2025-04-17T15:31:45.669Z",
        "lastAccessed": "2025-04-17T15:31:45.669Z"
    },
    {
        "key": "wd",
        "value": "360x634",
        "domain": "facebook.com",
        "path": "/",
        "hostOnly": false,
        "creation": "2025-04-17T15:31:45.669Z",
        "lastAccessed": "2025-04-17T15:31:45.669Z"
    },
    {
        "key": "locale",
        "value": "en_US",
        "domain": "facebook.com",
        "path": "/",
        "hostOnly": false,
        "creation": "2025-04-17T15:31:45.669Z",
        "lastAccessed": "2025-04-17T15:31:45.669Z"
    },
    {
        "key": "wl_cbv",
        "value": "v2%3Bclient_version%3A2790%3Btimestamp%3A1744903850",
        "domain": "facebook.com",
        "path": "/",
        "hostOnly": false,
        "creation": "2025-04-17T15:31:45.669Z",
        "lastAccessed": "2025-04-17T15:31:45.669Z"
    },
    {
        "key": "fbl_st",
        "value": "101432476%3BT%3A29081730",
        "domain": "facebook.com",
        "path": "/",
        "hostOnly": false,
        "creation": "2025-04-17T15:31:45.669Z",
        "lastAccessed": "2025-04-17T15:31:45.669Z"
    },
    {
        "key": "vpd",
        "value": "v1%3B357x360x3",
        "domain": "facebook.com",
        "path": "/",
        "hostOnly": false,
        "creation": "2025-04-17T15:31:45.669Z",
        "lastAccessed": "2025-04-17T15:31:45.669Z"
    }
]
